code_flags/__init__.py
code_flags/flag.py
code_flags/main.py
code_flags/mark.py
code_flags/utils.py
code_flags/loaders/__init__.py
code_flags/loaders/helpers.py
code_flags/loaders/json.py
code_flags/loaders/loader.py
code_flags/loaders/multi.py
code_flags/loaders/null.py
code_flags/loaders/proxy.py
code_flags/loaders/store.py
code_flags/loaders/toml.py
code_flags/loaders/yaml.py
code_flags/stores/__init__.py
code_flags/stores/env.py
code_flags/stores/in_memory.py
code_flags/stores/multi.py
code_flags/stores/proxy.py
code_flags/stores/redis.py
code_flags/stores/sqlalchemy.py
code_flags/stores/sqlite.py
code_flags/stores/store.py
feature_flags/__init__.py
feature_flags/flag.py
feature_flags/main.py
feature_flags/mark.py
feature_flags/utils.py
feature_flags/loaders/__init__.py
feature_flags/loaders/helpers.py
feature_flags/loaders/json.py
feature_flags/loaders/loader.py
feature_flags/loaders/multi.py
feature_flags/loaders/null.py
feature_flags/loaders/proxy.py
feature_flags/loaders/store.py
feature_flags/loaders/toml.py
feature_flags/loaders/yaml.py
feature_flags/stores/__init__.py
feature_flags/stores/env.py
feature_flags/stores/in_memory.py
feature_flags/stores/multi.py
feature_flags/stores/proxy.py
feature_flags/stores/redis.py
feature_flags/stores/sqlalchemy.py
feature_flags/stores/sqlite.py
feature_flags/stores/store.py
code_flags-0.1.0.dist-info/LICENSE
code_flags-0.1.0.dist-info/METADATA
code_flags-0.1.0.dist-info/WHEEL
code_flags-0.1.0.dist-info/top_level.txt
code_flags-0.1.0.dist-info/RECORD
