Metadata-Version: 2.1
Name: code-flags
Version: 0.1.0
Summary: Default template for PDM package
Author-email: Gustavo Cardoso <self.gustavocorrea@gmail.com>
License: MIT
Requires-Python: >=3.10
License-File: LICENSE
Requires-Dist: lazy-fields >=1.0.1
Requires-Dist: gyver-attrs >=0.9.3
Requires-Dist: typing-extensions >=4.12.0
Provides-Extra: env
Requires-Dist: env-star >=2.4.4 ; extra == 'env'
Provides-Extra: stores
Requires-Dist: redis >=5.0.4 ; extra == 'stores'
Requires-Dist: sqlalchemy >=2.0.30 ; extra == 'stores'
Provides-Extra: toml
Requires-Dist: tomlkit >=0.12.5 ; extra == 'toml'
Provides-Extra: yaml
Requires-Dist: yamllib >=0.0.1 ; extra == 'yaml'
